Workbook
Name Slicer_Category: #N/A
Name Slicer_Region: #N/A

Sheet Dashboard
B2: SALES PERFORMANCE DASHBOARD
B4: TOTAL SALES | G4: AVERAGE ORDER VALUE | L4: TOTAL PROFIT | Q4: TOTAL QUANTITY | V4: TOTAL ORDER
B6: =GETPIVOTDATA("Sum of Total_Sales",Pivot_KPI!$A$3) -> 712500 | G6: {=SUM(Data!I2:I26/COUNTA(Data!A2:A26))} -> 28500 | L6: =GETPIVOTDATA("Sum of Total_Profit",Pivot_KPI!$A$3) -> 162400 | Q6: =GETPIVOTDATA("Sum of Quantity",Pivot_KPI!$A$3) -> 108 | V6: =GETPIVOTDATA("Count of Order_ID",Pivot_KPI!$A$3) -> 25

Sheet Data
A1: Order_ID | B1: Order_Date | C1: Region | D1: Product | E1: Category | F1: Quantity | G1: Unit_Price | H1: Unit_Cost | I1: Total_Sales | J1: Total_Cost | K1: Total_Profit
A2: 1001 | B2: 46023 | C2: North | D2: Laptop | E2: Electronics | F2: 2 | G2: 50000 | H2: 40000 | I2: =Table1[[#This Row],[Quantity]]*Table1[[#This Row],[Unit_Price]] -> 100000 | J2: =Table1[[#This Row],[Quantity]]*Table1[[#This Row],[Unit_Cost]] -> 80000 | K2: =Table1[[#This Row],[Total_Sales]]-Table1[[#This Row],[Total_Cost]] -> 20000
A3: 1002 | B3: 46025 | C3: South | D3: Mouse | E3: Accessories | F3: 5 | G3: 500 | H3: 300 | I3: =Table1[[#This Row],[Quantity]]*Table1[[#This Row],[Unit_Price]] -> 2500 | J3: =Table1[[#This Row],[Quantity]]*Table1[[#This Row],[Unit_Cost]] -> 1500 | K3: =Table1[[#This Row],[Total_Sales]]-Table1[[#This Row],[Total_Cost]] -> 1000
A4: 1003 | B4: 46027 | C4: East | D4: Keyboard | E4: Accessories | F4: 3 | G4: 1200 | H4: 800 | I4: =Table1[[#This Row],[Quantity]]*Table1[[#This Row],[Unit_Price]] -> 3600 | J4: =Table1[[#This Row],[Quantity]]*Table1[[#This Row],[Unit_Cost]] -> 2400 | K4: =Table1[[#This Row],[Total_Sales]]-Table1[[#This Row],[Total_Cost]] -> 1200
A5: 1004 | B5: 46030 | C5: West | D5: Monitor | E5: Electronics | F5: 2 | G5: 12000 | H5: 9000 | I5: =Table1[[#This Row],[Quantity]]*Table1[[#This Row],[Unit_Price]] -> 24000 | J5: =Table1[[#This Row],[Quantity]]*Table1[[#This Row],[Unit_Cost]] -> 18000 | K5: =Table1[[#This Row],[Total_Sales]]-Table1[[#This Row],[Total_Cost]] -> 6000
A6: 1005 | B6: 46032 | C6: North | D6: Mouse | E6: Accessories | F6: 10 | G6: 500 | H6: 300 | I6: =Table1[[#This Row],[Quantity]]*Table1[[#This Row],[Unit_Price]] -> 5000 | J6: =Table1[[#This Row],[Quantity]]*Table1[[#This Row],[Unit_Cost]] -> 3000 | K6: =Table1[[#This Row],[Total_Sales]]-Table1[[#This Row],[Total_Cost]] -> 2000
A7: 1006 | B7: 46034 | C7: South | D7: Laptop | E7: Electronics | F7: 1 | G7: 50000 | H7: 40000 | I7: =Table1[[#This Row],[Quantity]]*Table1[[#This Row],[Unit_Price]] -> 50000 | J7: =Table1[[#This Row],[Quantity]]*Table1[[#This Row],[Unit_Cost]] -> 40000 | K7: =Table1[[#This Row],[Total_Sales]]-Table1[[#This Row],[Total_Cost]] -> 10000
A8: 1007 | B8: 46037 | C8: East | D8: Monitor | E8: Electronics | F8: 3 | G8: 12000 | H8: 9000 | I8: =Table1[[#This Row],[Quantity]]*Table1[[#This Row],[Unit_Price]] -> 36000 | J8: =Table1[[#This Row],[Quantity]]*Table1[[#This Row],[Unit_Cost]] -> 27000 | K8: =Table1[[#This Row],[Total_Sales]]-Table1[[#This Row],[Total_Cost]] -> 9000
A9: 1008 | B9: 46040 | C9: West | D9: Keyboard | E9: Accessories | F9: 6 | G9: 1200 | H9: 800 | I9: =Table1[[#This Row],[Quantity]]*Table1[[#This Row],[Unit_Price]] -> 7200 | J9: =Table1[[#This Row],[Quantity]]*Table1[[#This Row],[Unit_Cost]] -> 4800 | K9: =Table1[[#This Row],[Total_Sales]]-Table1[[#This Row],[Total_Cost]] -> 2400
A10: 1009 | B10: 46042 | C10: North | D10: Monitor | E10: Electronics | F10: 2 | G10: 12000 | H10: 9000 | I10: =Table1[[#This Row],[Quantity]]*Table1[[#This Row],[Unit_Price]] -> 24000 | J10: =Table1[[#This Row],[Quantity]]*Table1[[#This Row],[Unit_Cost]] -> 18000 | K10: =Table1[[#This Row],[Total_Sales]]-Table1[[#This Row],[Total_Cost]] -> 6000
A11: 1010 | B11: 46045 | C11: South | D11: Mouse | E11: Accessories | F11: 8 | G11: 500 | H11: 300 | I11: =Table1[[#This Row],[Quantity]]*Table1[[#This Row],[Unit_Price]] -> 4000 | J11: =Table1[[#This Row],[Quantity]]*Table1[[#This Row],[Unit_Cost]] -> 2400 | K11: =Table1[[#This Row],[Total_Sales]]-Table1[[#This Row],[Total_Cost]] -> 1600
A12: 1011 | B12: 46055 | C12: East | D12: Laptop | E12: Electronics | F12: 2 | G12: 50000 | H12: 40000 | I12: =Table1[[#This Row],[Quantity]]*Table1[[#This Row],[Unit_Price]] -> 100000 | J12: =Table1[[#This Row],[Quantity]]*Table1[[#This Row],[Unit_Cost]] -> 80000 | K12: =Table1[[#This Row],[Total_Sales]]-Table1[[#This Row],[Total_Cost]] -> 20000
A13: 1012 | B13: 46058 | C13: West | D13: Mouse | E13: Accessories | F13: 7 | G13: 500 | H13: 300 | I13: =Table1[[#This Row],[Quantity]]*Table1[[#This Row],[Unit_Price]] -> 3500 | J13: =Table1[[#This Row],[Quantity]]*Table1[[#This Row],[Unit_Cost]] -> 2100 | K13: =Table1[[#This Row],[Total_Sales]]-Table1[[#This Row],[Total_Cost]] -> 1400
... A26: 1025 | B26: 46102 | C26: North | D26: Mouse | E26: Accessories | F26: 6 | G26: 500 | H26: 300 | I26: =Table1[[#This Row],[Quantity]]*Table1[[#This Row],[Unit_Price]] -> 3000 | J26: =Table1[[#This Row],[Quantity]]*Table1[[#This Row],[Unit_Cost]] -> 1800 | K26: =Table1[[#This Row],[Total_Sales]]-Table1[[#This Row],[Total_Cost]] -> 1200

Sheet Pivot_KPI
A3: Sum of Total_Sales | B3: Sum of Total_Profit | C3: Sum of Quantity | D3: Count of Order_ID
A4: 712500 | B4: 162400 | C4: 108 | D4: 25

Sheet Pivot_Month
A3: Row Labels | B3: Sales | C3: Profit
A4: Jan | B4: 256300 | C4: 59200
A5: Feb | B5: 244300 | C5: 53400
A6: Mar | B6: 211900 | C6: 49800
A7: Grand Total | B7: 712500 | C7: 162400

Sheet Pivot_Category
A3: Row Labels | B3: Sum of Total_Sales
A4: Accessories | B4: 58500
A5: Electronics | B5: 654000
A6: Grand Total | B6: 712500

Sheet Pivot_Product
A3: Row Labels | B3: Sum of Total_Sales
A4: Keyboard | B4: 30000
A5: Laptop | B5: 450000
A6: Monitor | B6: 204000
A7: Mouse | B7: 28500
A8: Grand Total | B8: 712500

Sheet Pivot_Profit
A3: Row Labels | B3: Sum of Total_Profit
A4: Keyboard | B4: 10000
A5: Laptop | B5: 90000
A6: Monitor | B6: 51000
A7: Mouse | B7: 11400
A8: Grand Total | B8: 162400

Sheet Pivot_Region
A3: Row Labels | B3: Sum of Total_Sales
A4: West | B4: 101200
A5: South | B5: 186500
A6: East | B6: 202000
A7: North | B7: 222800
A8: Grand Total | B8: 712500
